NPLM/ANALYSISutils.py
NPLM/NNutils.py
NPLM/PLOTutils.py
NPLM/__init__.py
NPLM-0.0.6.dist-info/LICENSE
NPLM-0.0.6.dist-info/METADATA
NPLM-0.0.6.dist-info/WHEEL
NPLM-0.0.6.dist-info/top_level.txt
NPLM-0.0.6.dist-info/RECORD
