Metadata-Version: 2.1
Name: NPLM
Version: 0.0.6
Summary: package to run the New Physics Learning Machine (NPLM) algorithm.
Home-page: https://github.com/GaiaGrosso/NPLM_package
Author: Gaia Grosso
Author-email: gaia.grosso@cern.ch
License: UNKNOWN
Platform: UNKNOWN
Classifier: Programming Language :: Python :: 3
Classifier: License :: OSI Approved :: MIT License
Classifier: Operating System :: OS Independent
Requires-Python: >=3.6
License-File: LICENSE
